BayCal/__init__.py
BayCal/src/LikelihoodModel.py
BayCal/src/__init__.py
BayCal/src/LikelihoodModels/Factory.py
BayCal/src/LikelihoodModels/LikelihoodBase.py
BayCal/src/LikelihoodModels/NormalModel.py
BayCal/src/LikelihoodModels/__init__.py
baycal_ravenframework-1.0.0.dist-info/METADATA
baycal_ravenframework-1.0.0.dist-info/WHEEL
baycal_ravenframework-1.0.0.dist-info/top_level.txt
baycal_ravenframework-1.0.0.dist-info/RECORD
