Metadata-Version: 2.1
Name: baycal-ravenframework
Version: 1.0.0
Summary: BayCal plugin for RAVEN framework
Home-page: https://github.com/idaholab/BayCal
Requires-Python: >=3.7
Requires-Dist: raven-framework >=3.0
